{"_format":"","paths":{"artifacts":"out","build_infos":"out/build-info","sources":"src","tests":"test","scripts":"script","libraries":["lib"]},"files":{"lib/forge-std/src/Base.sol":{"lastModificationDate":1772874665889,"contentHash":"057da15af4544b7a","interfaceReprHash":null,"sourceName":"lib/forge-std/src/Base.sol","imports":["lib/forge-std/src/StdStorage.sol","lib/forge-std/src/Vm.sol"],"versionRequirement":">=0.8.13, <0.9.0","artifacts":{"CommonBase":{"0.8.33":{"default":{"path":"Base.sol\\CommonBase.json","build_id":"b9f68d431cc5b787"}}},"ScriptBase":{"0.8.33":{"default":{"path":"Base.sol\\ScriptBase.json","build_id":"b9f68d431cc5b787"}}},"TestBase":{"0.8.33":{"default":{"path":"Base.sol\\TestBase.json","build_id":"b9f68d431cc5b787"}}}},"seenByCompiler":true},"lib/forge-std/src/Script.sol":{"lastModificationDate":1772874665890,"contentHash":"f2808a0770d1b6a2","interfaceReprHash":null,"sourceName":"lib/forge-std/src/Script.sol","imports":["lib/forge-std/src/Base.sol","lib/forge-std/src/StdChains.sol","lib/forge-std/src/StdCheats.sol","lib/forge-std/src/StdConstants.sol","lib/forge-std/src/StdJson.sol","lib/forge-std/src/StdMath.sol","lib/forge-std/src/StdStorage.sol","lib/forge-std/src/StdStyle.sol","lib/forge-std/src/StdUtils.sol","lib/forge-std/src/Vm.sol","lib/forge-std/src/console.sol","lib/forge-std/src/console2.sol","lib/forge-std/src/interfaces/IMulticall3.sol","lib/forge-std/src/safeconsole.sol"],"versionRequirement":">=0.8.13, <0.9.0","artifacts":{"Script":{"0.8.33":{"default":{"path":"Script.sol\\Script.json","build_id":"626a5e8e73b47866"}}}},"seenByCompiler":true},"lib/forge-std/src/StdAssertions.sol":{"lastModificationDate":1772874665891,"contentHash":"7bf8f8dd736b7b28","interfaceReprHash":null,"sourceName":"lib/forge-std/src/StdAssertions.sol","imports":["lib/forge-std/src/Vm.sol"],"versionRequirement":">=0.8.13, <0.9.0","artifacts":{"StdAssertions":{"0.8.33":{"default":{"path":"StdAssertions.sol\\StdAssertions.json","build_id":"b9f68d431cc5b787"}}}},"seenByCompiler":true},"lib/forge-std/src/StdChains.sol":{"lastModificationDate":1772874665891,"contentHash":"cef85f092f883921","interfaceReprHash":null,"sourceName":"lib/forge-std/src/StdChains.sol","imports":["lib/forge-std/src/Vm.sol"],"versionRequirement":">=0.8.13, <0.9.0","artifacts":{"StdChains":{"0.8.33":{"default":{"path":"StdChains.sol\\StdChains.json","build_id":"b9f68d431cc5b787"}}}},"seenByCompiler":true},"lib/forge-std/src/StdCheats.sol":{"lastModificationDate":1772874665892,"contentHash":"906cd6276ed83364","interfaceReprHash":null,"sourceName":"lib/forge-std/src/StdCheats.sol","imports":["lib/forge-std/src/StdStorage.sol","lib/forge-std/src/Vm.sol","lib/forge-std/src/console.sol","lib/forge-std/src/console2.sol"],"versionRequirement":">=0.8.13, <0.9.0","artifacts":{"StdCheats":{"0.8.33":{"default":{"path":"StdCheats.sol\\StdCheats.json","build_id":"b9f68d431cc5b787"}}},"StdCheatsSafe":{"0.8.33":{"default":{"path":"StdCheats.sol\\StdCheatsSafe.json","build_id":"b9f68d431cc5b787"}}}},"seenByCompiler":true},"lib/forge-std/src/StdConstants.sol":{"lastModificationDate":1772874665892,"contentHash":"6e64e3e0f1e270b1","interfaceReprHash":null,"sourceName":"lib/forge-std/src/StdConstants.sol","imports":["lib/forge-std/src/Vm.sol","lib/forge-std/src/interfaces/IMulticall3.sol"],"versionRequirement":">=0.8.13, <0.9.0","artifacts":{"StdConstants":{"0.8.33":{"default":{"path":"StdConstants.sol\\StdConstants.json","build_id":"b9f68d431cc5b787"}}}},"seenByCompiler":true},"lib/forge-std/src/StdError.sol":{"lastModificationDate":1772874665893,"contentHash":"aa3090ae1422ce31","interfaceReprHash":null,"sourceName":"lib/forge-std/src/StdError.sol","imports":[],"versionRequirement":">=0.8.13, <0.9.0","artifacts":{"stdError":{"0.8.33":{"default":{"path":"StdError.sol\\stdError.json","build_id":"b9f68d431cc5b787"}}}},"seenByCompiler":true},"lib/forge-std/src/StdInvariant.sol":{"lastModificationDate":1772874665893,"contentHash":"65ff1041945c2df0","interfaceReprHash":null,"sourceName":"lib/forge-std/src/StdInvariant.sol","imports":[],"versionRequirement":">=0.8.13, <0.9.0","artifacts":{"StdInvariant":{"0.8.33":{"default":{"path":"StdInvariant.sol\\StdInvariant.json","build_id":"b9f68d431cc5b787"}}}},"seenByCompiler":true},"lib/forge-std/src/StdJson.sol":{"lastModificationDate":1772874665893,"contentHash":"deb75521f38fb99f","interfaceReprHash":null,"sourceName":"lib/forge-std/src/StdJson.sol","imports":["lib/forge-std/src/Vm.sol"],"versionRequirement":">=0.8.13, <0.9.0","artifacts":{"stdJson":{"0.8.33":{"default":{"path":"StdJson.sol\\stdJson.json","build_id":"b9f68d431cc5b787"}}}},"seenByCompiler":true},"lib/forge-std/src/StdMath.sol":{"lastModificationDate":1772874665893,"contentHash":"393b2ec0becc479a","interfaceReprHash":null,"sourceName":"lib/forge-std/src/StdMath.sol","imports":[],"versionRequirement":">=0.8.13, <0.9.0","artifacts":{"stdMath":{"0.8.33":{"default":{"path":"StdMath.sol\\stdMath.json","build_id":"b9f68d431cc5b787"}}}},"seenByCompiler":true},"lib/forge-std/src/StdStorage.sol":{"lastModificationDate":1772874665894,"contentHash":"8b834c63078a7790","interfaceReprHash":null,"sourceName":"lib/forge-std/src/StdStorage.sol","imports":["lib/forge-std/src/Vm.sol"],"versionRequirement":">=0.8.13, <0.9.0","artifacts":{"stdStorage":{"0.8.33":{"default":{"path":"StdStorage.sol\\stdStorage.json","build_id":"b9f68d431cc5b787"}}},"stdStorageSafe":{"0.8.33":{"default":{"path":"StdStorage.sol\\stdStorageSafe.json","build_id":"b9f68d431cc5b787"}}}},"seenByCompiler":true},"lib/forge-std/src/StdStyle.sol":{"lastModificationDate":1772874665894,"contentHash":"dd683e581612d9d7","interfaceReprHash":null,"sourceName":"lib/forge-std/src/StdStyle.sol","imports":["lib/forge-std/src/Vm.sol"],"versionRequirement":">=0.8.13, <0.9.0","artifacts":{"StdStyle":{"0.8.33":{"default":{"path":"StdStyle.sol\\StdStyle.json","build_id":"b9f68d431cc5b787"}}}},"seenByCompiler":true},"lib/forge-std/src/StdToml.sol":{"lastModificationDate":1772874665894,"contentHash":"66561afcd2e48189","interfaceReprHash":null,"sourceName":"lib/forge-std/src/StdToml.sol","imports":["lib/forge-std/src/Vm.sol"],"versionRequirement":">=0.8.13, <0.9.0","artifacts":{"stdToml":{"0.8.33":{"default":{"path":"StdToml.sol\\stdToml.json","build_id":"b9f68d431cc5b787"}}}},"seenByCompiler":true},"lib/forge-std/src/StdUtils.sol":{"lastModificationDate":1772874665895,"contentHash":"476c1e8becd32967","interfaceReprHash":null,"sourceName":"lib/forge-std/src/StdUtils.sol","imports":["lib/forge-std/src/StdConstants.sol","lib/forge-std/src/Vm.sol","lib/forge-std/src/interfaces/IMulticall3.sol"],"versionRequirement":">=0.8.13, <0.9.0","artifacts":{"StdUtils":{"0.8.33":{"default":{"path":"StdUtils.sol\\StdUtils.json","build_id":"b9f68d431cc5b787"}}}},"seenByCompiler":true},"lib/forge-std/src/Test.sol":{"lastModificationDate":1772874665895,"contentHash":"bd0e131f71fa5665","interfaceReprHash":null,"sourceName":"lib/forge-std/src/Test.sol","imports":["lib/forge-std/src/Base.sol","lib/forge-std/src/StdAssertions.sol","lib/forge-std/src/StdChains.sol","lib/forge-std/src/StdCheats.sol","lib/forge-std/src/StdConstants.sol","lib/forge-std/src/StdError.sol","lib/forge-std/src/StdInvariant.sol","lib/forge-std/src/StdJson.sol","lib/forge-std/src/StdMath.sol","lib/forge-std/src/StdStorage.sol","lib/forge-std/src/StdStyle.sol","lib/forge-std/src/StdToml.sol","lib/forge-std/src/StdUtils.sol","lib/forge-std/src/Vm.sol","lib/forge-std/src/console.sol","lib/forge-std/src/console2.sol","lib/forge-std/src/interfaces/IMulticall3.sol","lib/forge-std/src/safeconsole.sol"],"versionRequirement":">=0.8.13, <0.9.0","artifacts":{"Test":{"0.8.33":{"default":{"path":"Test.sol\\Test.json","build_id":"b9f68d431cc5b787"}}}},"seenByCompiler":true},"lib/forge-std/src/Vm.sol":{"lastModificationDate":1772874665896,"contentHash":"55e749aafb49ce93","interfaceReprHash":null,"sourceName":"lib/forge-std/src/Vm.sol","imports":[],"versionRequirement":">=0.8.13, <0.9.0","artifacts":{"Vm":{"0.8.33":{"default":{"path":"Vm.sol\\Vm.json","build_id":"b9f68d431cc5b787"}}},"VmSafe":{"0.8.33":{"default":{"path":"Vm.sol\\VmSafe.json","build_id":"b9f68d431cc5b787"}}}},"seenByCompiler":true},"lib/forge-std/src/console.sol":{"lastModificationDate":1772874665897,"contentHash":"c2f250cceea75093","interfaceReprHash":null,"sourceName":"lib/forge-std/src/console.sol","imports":[],"versionRequirement":">=0.8.13, <0.9.0","artifacts":{"console":{"0.8.33":{"default":{"path":"console.sol\\console.json","build_id":"b9f68d431cc5b787"}}}},"seenByCompiler":true},"lib/forge-std/src/console2.sol":{"lastModificationDate":1772874665897,"contentHash":"fb84555cebe27360","interfaceReprHash":null,"sourceName":"lib/forge-std/src/console2.sol","imports":["lib/forge-std/src/console.sol"],"versionRequirement":">=0.8.13, <0.9.0","artifacts":{},"seenByCompiler":true},"lib/forge-std/src/interfaces/IMulticall3.sol":{"lastModificationDate":1772874665900,"contentHash":"731463c8fd01e759","interfaceReprHash":null,"sourceName":"lib/forge-std/src/interfaces/IMulticall3.sol","imports":[],"versionRequirement":">=0.8.13, <0.9.0","artifacts":{"IMulticall3":{"0.8.33":{"default":{"path":"IMulticall3.sol\\IMulticall3.json","build_id":"b9f68d431cc5b787"}}}},"seenByCompiler":true},"lib/forge-std/src/safeconsole.sol":{"lastModificationDate":1772874665901,"contentHash":"075ad54247fa474a","interfaceReprHash":null,"sourceName":"lib/forge-std/src/safeconsole.sol","imports":[],"versionRequirement":">=0.8.13, <0.9.0","artifacts":{"safeconsole":{"0.8.33":{"default":{"path":"safeconsole.sol\\safeconsole.json","build_id":"b9f68d431cc5b787"}}}},"seenByCompiler":true},"lib/openzeppelin-contracts/contracts/access/Ownable.sol":{"lastModificationDate":1772874910825,"contentHash":"aeede215495e3727","interfaceReprHash":null,"sourceName":"lib/openzeppelin-contracts/contracts/access/Ownable.sol","imports":["lib/openzeppelin-contracts/contracts/utils/Context.sol"],"versionRequirement":"^0.8.20","artifacts":{"Ownable":{"0.8.33":{"default":{"path":"Ownable.sol\\Ownable.json","build_id":"b9f68d431cc5b787"}}}},"seenByCompiler":true},"lib/openzeppelin-contracts/contracts/interfaces/draft-IERC6093.sol":{"lastModificationDate":1772874910864,"contentHash":"3902bd8df0571165","interfaceReprHash":null,"sourceName":"lib/openzeppelin-contracts/contracts/interfaces/draft-IERC6093.sol","imports":[],"versionRequirement":">=0.8.4","artifacts":{"IERC1155Errors":{"0.8.33":{"default":{"path":"draft-IERC6093.sol\\IERC1155Errors.json","build_id":"b9f68d431cc5b787"}}},"IERC20Errors":{"0.8.33":{"default":{"path":"draft-IERC6093.sol\\IERC20Errors.json","build_id":"b9f68d431cc5b787"}}},"IERC721Errors":{"0.8.33":{"default":{"path":"draft-IERC6093.sol\\IERC721Errors.json","build_id":"b9f68d431cc5b787"}}}},"seenByCompiler":true},"lib/openzeppelin-contracts/contracts/token/ERC20/ERC20.sol":{"lastModificationDate":1772874910915,"contentHash":"bdb8cc1da86cf7dd","interfaceReprHash":null,"sourceName":"lib/openzeppelin-contracts/contracts/token/ERC20/ERC20.sol","imports":["lib/openzeppelin-contracts/contracts/interfaces/draft-IERC6093.sol","lib/openzeppelin-contracts/contracts/token/ERC20/IERC20.sol","lib/openzeppelin-contracts/contracts/token/ERC20/extensions/IERC20Metadata.sol","lib/openzeppelin-contracts/contracts/utils/Context.sol"],"versionRequirement":"^0.8.20","artifacts":{"ERC20":{"0.8.33":{"default":{"path":"ERC20.sol\\ERC20.json","build_id":"b9f68d431cc5b787"}}}},"seenByCompiler":true},"lib/openzeppelin-contracts/contracts/token/ERC20/IERC20.sol":{"lastModificationDate":1772874910916,"contentHash":"1dcd768972ff31b3","interfaceReprHash":null,"sourceName":"lib/openzeppelin-contracts/contracts/token/ERC20/IERC20.sol","imports":[],"versionRequirement":">=0.4.16","artifacts":{"IERC20":{"0.8.33":{"default":{"path":"IERC20.sol\\IERC20.json","build_id":"b9f68d431cc5b787"}}}},"seenByCompiler":true},"lib/openzeppelin-contracts/contracts/token/ERC20/extensions/IERC20Metadata.sol":{"lastModificationDate":1772874910919,"contentHash":"c0fde354a75fbdc6","interfaceReprHash":null,"sourceName":"lib/openzeppelin-contracts/contracts/token/ERC20/extensions/IERC20Metadata.sol","imports":["lib/openzeppelin-contracts/contracts/token/ERC20/IERC20.sol"],"versionRequirement":">=0.6.2","artifacts":{"IERC20Metadata":{"0.8.33":{"default":{"path":"IERC20Metadata.sol\\IERC20Metadata.json","build_id":"b9f68d431cc5b787"}}}},"seenByCompiler":true},"lib/openzeppelin-contracts/contracts/utils/Context.sol":{"lastModificationDate":1772874910933,"contentHash":"16db1f8b2f7183f5","interfaceReprHash":null,"sourceName":"lib/openzeppelin-contracts/contracts/utils/Context.sol","imports":[],"versionRequirement":"^0.8.20","artifacts":{"Context":{"0.8.33":{"default":{"path":"Context.sol\\Context.json","build_id":"b9f68d431cc5b787"}}}},"seenByCompiler":true},"lib/openzeppelin-contracts/contracts/utils/ReentrancyGuard.sol":{"lastModificationDate":1772874910938,"contentHash":"a70644ba3ffaf8d5","interfaceReprHash":null,"sourceName":"lib/openzeppelin-contracts/contracts/utils/ReentrancyGuard.sol","imports":["lib/openzeppelin-contracts/contracts/utils/StorageSlot.sol"],"versionRequirement":"^0.8.20","artifacts":{"ReentrancyGuard":{"0.8.33":{"default":{"path":"ReentrancyGuard.sol\\ReentrancyGuard.json","build_id":"831f42aa592fd13f"}}}},"seenByCompiler":true},"lib/openzeppelin-contracts/contracts/utils/StorageSlot.sol":{"lastModificationDate":1772874910940,"contentHash":"261e9fcb6515866e","interfaceReprHash":null,"sourceName":"lib/openzeppelin-contracts/contracts/utils/StorageSlot.sol","imports":[],"versionRequirement":"^0.8.20","artifacts":{"StorageSlot":{"0.8.33":{"default":{"path":"StorageSlot.sol\\StorageSlot.json","build_id":"831f42aa592fd13f"}}}},"seenByCompiler":true},"script/Counter.s.sol":{"lastModificationDate":1772960248199,"contentHash":"dc609d4e770474de","interfaceReprHash":null,"sourceName":"script/Counter.s.sol","imports":["lib/forge-std/src/Base.sol","lib/forge-std/src\\Script.sol","lib/forge-std/src/StdChains.sol","lib/forge-std/src/StdCheats.sol","lib/forge-std/src/StdConstants.sol","lib/forge-std/src/StdJson.sol","lib/forge-std/src/StdMath.sol","lib/forge-std/src/StdStorage.sol","lib/forge-std/src/StdStyle.sol","lib/forge-std/src/StdUtils.sol","lib/forge-std/src/Vm.sol","lib/forge-std/src/console.sol","lib/forge-std/src/console2.sol","lib/forge-std/src/interfaces/IMulticall3.sol","lib/forge-std/src/safeconsole.sol","lib/openzeppelin-contracts/contracts\\access/Ownable.sol","lib/openzeppelin-contracts/contracts/interfaces/draft-IERC6093.sol","lib/openzeppelin-contracts/contracts\\token/ERC20/ERC20.sol","lib/openzeppelin-contracts/contracts/token/ERC20/IERC20.sol","lib/openzeppelin-contracts/contracts/token/ERC20/extensions/IERC20Metadata.sol","lib/openzeppelin-contracts/contracts/utils/Context.sol","lib/openzeppelin-contracts/contracts\\utils/ReentrancyGuard.sol","lib/openzeppelin-contracts/contracts/utils/StorageSlot.sol","src\\Counter.sol"],"versionRequirement":"^0.8.20","artifacts":{"CounterScript":{"0.8.33":{"default":{"path":"Counter.s.sol\\CounterScript.json","build_id":"831f42aa592fd13f"}}}},"seenByCompiler":true},"src/Counter.sol":{"lastModificationDate":1773677788382,"contentHash":"cacab30e2b23ceca","interfaceReprHash":null,"sourceName":"src/Counter.sol","imports":["lib/openzeppelin-contracts/contracts\\access/Ownable.sol","lib/openzeppelin-contracts/contracts/interfaces/draft-IERC6093.sol","lib/openzeppelin-contracts/contracts\\token/ERC20/ERC20.sol","lib/openzeppelin-contracts/contracts/token/ERC20/IERC20.sol","lib/openzeppelin-contracts/contracts/token/ERC20/extensions/IERC20Metadata.sol","lib/openzeppelin-contracts/contracts/utils/Context.sol","lib/openzeppelin-contracts/contracts\\utils/ReentrancyGuard.sol","lib/openzeppelin-contracts/contracts/utils/StorageSlot.sol"],"versionRequirement":"^0.8.20","artifacts":{"MemeCoin":{"0.8.33":{"default":{"path":"Counter.sol\\MemeCoin.json","build_id":"831f42aa592fd13f"}}},"MemeCoinLaunchPad":{"0.8.33":{"default":{"path":"Counter.sol\\MemeCoinLaunchPad.json","build_id":"831f42aa592fd13f"}}}},"seenByCompiler":true}},"builds":["626a5e8e73b47866","831f42aa592fd13f","b9f68d431cc5b787"],"profiles":{"default":{"solc":{"optimizer":{"enabled":false,"runs":200},"metadata":{"useLiteralContent":false,"bytecodeHash":"ipfs","appendCBOR":true},"outputSelection":{"*":{"*":["abi","evm.bytecode.object","evm.bytecode.sourceMap","evm.bytecode.linkReferences","evm.deployedBytecode.object","evm.deployedBytecode.sourceMap","evm.deployedBytecode.linkReferences","evm.deployedBytecode.immutableReferences","evm.methodIdentifiers","metadata"]}},"evmVersion":"prague","viaIR":false,"libraries":{}},"vyper":{"evmVersion":"prague","outputSelection":{"*":{"*":["abi","evm.bytecode","evm.deployedBytecode"]}}}}},"preprocessed":false,"mocks":[]}